sphinx_theme/__init__.py
sphinx_theme/neo_rtd_theme/breadcrumbs.html
sphinx_theme/neo_rtd_theme/footer.html
sphinx_theme/neo_rtd_theme/layout.html
sphinx_theme/neo_rtd_theme/layout_old.html
sphinx_theme/neo_rtd_theme/search.html
sphinx_theme/neo_rtd_theme/searchbox.html
sphinx_theme/neo_rtd_theme/theme.conf
sphinx_theme/neo_rtd_theme/versions.html
sphinx_theme/neo_rtd_theme/static/css/badge_only.css
sphinx_theme/neo_rtd_theme/static/css/copied_wy_variables.css
sphinx_theme/neo_rtd_theme/static/css/theme.css
sphinx_theme/neo_rtd_theme/static/fonts/Inconsolata-Bold.ttf
sphinx_theme/neo_rtd_theme/static/fonts/Inconsolata-Regular.ttf
sphinx_theme/neo_rtd_theme/static/fonts/Lato-Bold.ttf
sphinx_theme/neo_rtd_theme/static/fonts/Lato-Regular.ttf
sphinx_theme/neo_rtd_theme/static/fonts/RobotoSlab-Bold.ttf
sphinx_theme/neo_rtd_theme/static/fonts/RobotoSlab-Regular.ttf
sphinx_theme/neo_rtd_theme/static/fonts/UbuntuMono-Bold.ttf
sphinx_theme/neo_rtd_theme/static/fonts/UbuntuMono-BoldItalic.ttf
sphinx_theme/neo_rtd_theme/static/fonts/UbuntuMono-Italic.ttf
sphinx_theme/neo_rtd_theme/static/fonts/UbuntuMono-Regular.ttf
sphinx_theme/neo_rtd_theme/static/fonts/fontawesome-webfont.eot
sphinx_theme/neo_rtd_theme/static/fonts/fontawesome-webfont.svg
sphinx_theme/neo_rtd_theme/static/fonts/fontawesome-webfont.ttf
sphinx_theme/neo_rtd_theme/static/fonts/fontawesome-webfont.woff
sphinx_theme/neo_rtd_theme/static/js/modernizr.min.js
sphinx_theme/neo_rtd_theme/static/js/theme.js
sphinx_theme/stanford_theme/breadcrumbs.html
sphinx_theme/stanford_theme/footer.html
sphinx_theme/stanford_theme/layout.html
sphinx_theme/stanford_theme/layout_old.html
sphinx_theme/stanford_theme/search.html
sphinx_theme/stanford_theme/searchbox.html
sphinx_theme/stanford_theme/theme.conf
sphinx_theme/stanford_theme/versions.html
sphinx_theme/stanford_theme/static/css/badge_only.css
sphinx_theme/stanford_theme/static/css/copied_wy_variables.css
sphinx_theme-1.0.dist-info/DESCRIPTION.rst
sphinx_theme-1.0.dist-info/METADATA
sphinx_theme-1.0.dist-info/RECORD
sphinx_theme-1.0.dist-info/WHEEL
sphinx_theme-1.0.dist-info/metadata.json
sphinx_theme-1.0.dist-info/top_level.txt
