Metadata-Version: 2.0
Name: sphinx-theme
Version: 1.0
Summary: Sphinx documentation theme based on readthedocs.org
Home-page: https://github.com/LinxiFan/Sphinx-theme/
Author: Linxi (Jim) Fan
Author-email: jimfan@cs.stanford.edu
License: MIT
Platform: UNKNOWN
Classifier: Development Status :: 5 - Production/Stable
Classifier: Environment :: Console
Classifier: Environment :: Web Environment
Classifier: Programming Language :: Python :: 2.7
Classifier: Programming Language :: Python :: 3
Classifier: Operating System :: OS Independent
Classifier: Topic :: Documentation
Classifier: Topic :: Software Development :: Documentation
